texiteasy/LICENSE.txt
texiteasy/README.md
texiteasy/__init__.py
texiteasy/escape.py
texiteasy-0.0.1b0.dist-info/WHEEL
texiteasy-0.0.1b0.dist-info/METADATA
texiteasy-0.0.1b0.dist-info/RECORD
