Metadata-Version: 2.1
Name: texiteasy
Version: 0.0.1b0
Summary: This project contains tools to work with LaTeX.
Home-page: https://github.com/projetmbc/tools-for-latex/tree/master/TeXitEasy
License: GNU License Version 3
Author: Christophe BAL
Maintainer: Christophe BAL
Requires-Python: >=3.8,<4.0
Classifier: License :: Other/Proprietary License
Classifier: Programming Language :: Python :: 3
Classifier: Programming Language :: Python :: 3.8
Classifier: Programming Language :: Python :: 3.9
Project-URL: Repository, https://github.com/projetmbc/tools-for-latex/tree/master/TeXitEasy
